ai_drift-0.10.0.dist-info/licenses/LICENSE
drift/__init__.py
drift/__main__.py
drift/cache.py
drift/agent_tools/__init__.py
drift/agent_tools/base.py
drift/agent_tools/claude_code.py
drift/cli/__init__.py
drift/cli/logging_config.py
drift/cli/main.py
drift/cli/utils.py
drift/cli/commands/__init__.py
drift/cli/commands/analyze.py
drift/cli/commands/document.py
drift/cli/commands/draft.py
drift/cli/commands/list.py
drift/cli/output/__init__.py
drift/cli/output/formatter.py
drift/cli/output/json.py
drift/cli/output/markdown.py
drift/config/__init__.py
drift/config/defaults.py
drift/config/loader.py
drift/config/models.py
drift/core/__init__.py
drift/core/analyzer.py
drift/core/types.py
drift/documents/__init__.py
drift/documents/loader.py
drift/draft/__init__.py
drift/draft/checker.py
drift/draft/eligibility.py
drift/draft/generator.py
drift/draft/resolver.py
drift/providers/__init__.py
drift/providers/anthropic.py
drift/providers/base.py
drift/providers/bedrock.py
drift/providers/claude_code.py
drift/utils/__init__.py
drift/utils/claude_dependency_graph.py
drift/utils/dependency_graph.py
drift/utils/frontmatter.py
drift/utils/link_validator.py
drift/utils/temp.py
drift/validation/__init__.py
drift/validation/params.py
drift/validation/patterns.py
drift/validation/validators/__init__.py
drift/validation/validators/base.py
drift/validation/validators/client/__init__.py
drift/validation/validators/client/claude.py
drift/validation/validators/client/claude_dependency.py
drift/validation/validators/core/__init__.py
drift/validation/validators/core/block_validators.py
drift/validation/validators/core/circular_dependencies_validator.py
drift/validation/validators/core/dependency_validators.py
drift/validation/validators/core/file_validators.py
drift/validation/validators/core/format_validators.py
drift/validation/validators/core/list_validators.py
drift/validation/validators/core/markdown_validators.py
drift/validation/validators/core/max_dependency_depth_validator.py
ai_drift-0.10.0.dist-info/METADATA
ai_drift-0.10.0.dist-info/WHEEL
ai_drift-0.10.0.dist-info/entry_points.txt
ai_drift-0.10.0.dist-info/top_level.txt
ai_drift-0.10.0.dist-info/RECORD
