Metadata-Version: 2.4
Name: ai-drift
Version: 0.10.0
Summary: TDD framework for AI workflows - define agent/skill/command standards in .drift.yaml and validate project structure programmatically
Author-email: Jim Rosser <me@j4r.wtf>
License: MIT
Project-URL: Homepage, https://github.com/jarosser06/drift
Project-URL: Repository, https://github.com/jarosser06/drift
Project-URL: Issues, https://github.com/jarosser06/drift/issues
Project-URL: Documentation, https://docs.driftai.dev
Keywords: ai,aisdl,sldcv2,tdd,validation,workflow,agent,claude,drift,quality-assurance
Classifier: Intended Audience :: Developers
Classifier: License :: OSI Approved :: MIT License
Classifier: Programming Language :: Python :: 3
Classifier: Programming Language :: Python :: 3.10
Classifier: Programming Language :: Python :: 3.11
Classifier: Programming Language :: Python :: 3.12
Requires-Python: >=3.10
License-File: LICENSE
Requires-Dist: pydantic<3.0.0,>=2.5.0
Requires-Dist: pydantic-settings<3.0.0,>=2.1.0
Requires-Dist: anthropic<1.0.0,>=0.75.0
Requires-Dist: boto3<2.0.0,>=1.34.0
Requires-Dist: pyyaml<7.0.0,>=6.0.0
Requires-Dist: python-dateutil<3.0.0,>=2.8.0
Requires-Dist: requests<3.0.0,>=2.31.0
Requires-Dist: jsonschema<5.0.0,>=4.0.0
Provides-Extra: dev
Requires-Dist: pytest<8.0.0,>=7.4.0; extra == "dev"
Requires-Dist: pytest-cov<5.0.0,>=4.1.0; extra == "dev"
Requires-Dist: pytest-mock<4.0.0,>=3.12.0; extra == "dev"
Requires-Dist: pytest-asyncio<0.22.0,>=0.21.0; extra == "dev"
Requires-Dist: mypy<2.0.0,>=1.7.0; extra == "dev"
Requires-Dist: types-pyyaml<7.0.0,>=6.0.0; extra == "dev"
Requires-Dist: types-python-dateutil<3.0.0,>=2.8.0; extra == "dev"
Requires-Dist: types-requests<3.0.0,>=2.31.0; extra == "dev"
Requires-Dist: black<24.0.0,>=23.12.0; extra == "dev"
Requires-Dist: flake8<7.0.0,>=6.1.0; extra == "dev"
Requires-Dist: flake8-docstrings<2.0.0,>=1.7.0; extra == "dev"
Requires-Dist: isort<6.0.0,>=5.13.0; extra == "dev"
Requires-Dist: build<2.0.0,>=1.0.0; extra == "dev"
Requires-Dist: twine<6.0.0,>=4.0.0; extra == "dev"
Requires-Dist: pkginfo>=1.12.0; extra == "dev"
Provides-Extra: docs
Requires-Dist: sphinx>=7.0.0; extra == "docs"
Requires-Dist: sphinx-rtd-theme>=2.0.0; extra == "docs"
Requires-Dist: sphinx-autodoc-typehints>=1.25.0; extra == "docs"
Requires-Dist: myst-parser>=2.0.0; extra == "docs"
Dynamic: license-file
